renko.py
renko-0.0.16.dist-info/LICENSE.txt
renko-0.0.16.dist-info/METADATA
renko-0.0.16.dist-info/WHEEL
renko-0.0.16.dist-info/top_level.txt
renko-0.0.16.dist-info/RECORD
