Metadata-Version: 2.1
Name: renko
Version: 0.0.16
Summary: Renko chart creator.
Home-page: https://github.com/aticio/renko
Author: Özgür Atıcı
Author-email: aticiozgur@gmail.com
License: UNKNOWN
Platform: UNKNOWN
Classifier: Programming Language :: Python :: 3
Classifier: License :: OSI Approved :: MIT License
Classifier: Operating System :: OS Independent
Provides-Extra: dev
